MANIFEST.in
README.md
env.py
requirements.txt
run.py
setup.py
docker/base.Dockerfile
docker/build_base.sh
docker/build_rest.sh
docker/build_rpc.sh
docker/rest.Dockerfile
docker/rpc.Dockerfile
tests/__init__.py
tests/test_rpc_client.py
validation_scripting_engine.egg-info/PKG-INFO
validation_scripting_engine.egg-info/SOURCES.txt
validation_scripting_engine.egg-info/dependency_links.txt
validation_scripting_engine.egg-info/top_level.txt
vse/__init__.py
vse/__main__.py
vse/api/__init__.py
vse/api/rest/__init__.py
vse/api/rpc/__init__.py
vse/api/rpc/client.py
vse/api/rpc/services/__init__.py
vse/api/rpc/services/vse.py
vse/api/rpc/services/schemas/__init__.py
vse/core/__init__.py
vse/core/audit.py
vse/core/constants.py
vse/core/exceptions.py
vse/core/mapping_agent.py
vse/core/maps.py
vse/core/task.py
vse/handlers/__init__.py
vse/handlers/base.py
vse/handlers/ciscoconfparse.py
vse/handlers/test.py
vse/handlers/schemas/__init__.py
vse/handlers/schemas/ciscoconfparse.py
vse/models/__init__.py
vse/wrappers/__init__.py
vse/wrappers/ssh_cmd.py
vse/wrappers/ssh_config.py