Metadata-Version: 1.0
Name: validation-scripting-engine
Version: 1.0
Summary: Validation Scripting Engine
Home-page: UNKNOWN
Author: Courtney S Baxter Jr
Author-email: cbaxtertech@gmail.com
License: UNKNOWN
Platform: UNKNOWN
